triplet_extract/__init__.py
triplet_extract/corenlp_patterns.py
triplet_extract/extractor.py
triplet_extract/normalizer.py
triplet_extract/models/affinities/obj.tab.gz
triplet_extract/models/affinities/pp.tab.gz
triplet_extract/models/affinities/subj_obj_pp.tab.gz
triplet_extract/models/affinities/subj_pp.tab.gz
triplet_extract/models/affinities/subj_pp_obj.tab.gz
triplet_extract/models/affinities/subj_pp_pp.tab.gz
triplet_extract/models/clause_model/clauseSearcherModel.ser.gz
triplet_extract/models/clause_model/extracted_model.json
triplet_extract/models/clause_model/extracted_model.pkl
triplet_extract/openie/__init__.py
triplet_extract/openie/affinity_models.py
triplet_extract/openie/aux_filter.py
triplet_extract/openie/clause_featurizer.py
triplet_extract/openie/clause_search_state.py
triplet_extract/openie/clause_splitter.py
triplet_extract/openie/dependency_relations.py
triplet_extract/openie/forward_entailer.py
triplet_extract/openie/gpu_batch_reparser.py
triplet_extract/openie/linear_classifier.py
triplet_extract/openie/natural_logic_weights.py
triplet_extract/openie/operator.py
triplet_extract/openie/operator_spec.py
triplet_extract/openie/polarity.py
triplet_extract/openie/polarity_annotator.py
triplet_extract/openie/sentence_fragment.py
triplet_extract/openie/text_utils.py
triplet_extract/preprocessing/__init__.py
triplet_extract/preprocessing/latex_component.py
triplet_extract/preprocessing/latex_handler.py
triplet_extract-0.2.0.dist-info/licenses/LICENSE
triplet_extract-0.2.0.dist-info/METADATA
triplet_extract-0.2.0.dist-info/WHEEL
triplet_extract-0.2.0.dist-info/top_level.txt
triplet_extract-0.2.0.dist-info/RECORD
