Metadata-Version: 2.4
Name: triplet-extract
Version: 0.2.0
Summary: Pure Python triplet extraction based on Stanford OpenIE
Author-email: Adrian Lucas Malec <dradrian@gmail.com>
License: GPL-3.0-or-later
Project-URL: Homepage, https://github.com/adlumal/triplet-extract
Project-URL: Repository, https://github.com/adlumal/triplet-extract
Project-URL: Issues, https://github.com/adlumal/triplet-extract/issues
Project-URL: Original Paper, http://nlp.stanford.edu/pubs/2015angeli-openie.pdf
Project-URL: Stanford OpenIE, https://nlp.stanford.edu/software/openie.html
Keywords: nlp,information-extraction,openie,triplets,knowledge-graph,stanford,relation-extraction
Classifier: Development Status :: 4 - Beta
Classifier: Intended Audience :: Developers
Classifier: Intended Audience :: Science/Research
Classifier: License :: OSI Approved :: GNU General Public License v3 or later (GPLv3+)
Classifier: Programming Language :: Python :: 3
Classifier: Programming Language :: Python :: 3.10
Classifier: Programming Language :: Python :: 3.11
Classifier: Programming Language :: Python :: 3.12
Classifier: Programming Language :: Python :: 3.13
Classifier: Topic :: Scientific/Engineering :: Artificial Intelligence
Classifier: Topic :: Text Processing :: Linguistic
Requires-Python: >=3.10
License-File: LICENSE
Requires-Dist: spacy>=3.5.0
Requires-Dist: javaobj-py3>=0.4.4
Provides-Extra: progress
Requires-Dist: tqdm>=4.65.0; extra == "progress"
Provides-Extra: deepsearch
Requires-Dist: cupy-cuda12x>=12.0.0; platform_system != "Darwin" and extra == "deepsearch"
Requires-Dist: spacy[cuda12x]>=3.5.0; platform_system != "Darwin" and extra == "deepsearch"
Provides-Extra: dev
Requires-Dist: pytest>=7.0.0; extra == "dev"
Requires-Dist: black>=24.0.0; extra == "dev"
Requires-Dist: ruff>=0.1.0; extra == "dev"
Dynamic: license-file
